iET/__init__.py
iET/compute_attribution_function.py
iET/iET.py
iET/iet_functions.py
iET-1.2.9.dist-info/METADATA
iET-1.2.9.dist-info/WHEEL
iET-1.2.9.dist-info/top_level.txt
iET-1.2.9.dist-info/RECORD
