Metadata-Version: 2.1
Name: iET
Version: 1.2.9
Summary: iET - iterative Expected Target
Home-page: https://github.com/dandolodavid/iET
Author: Dandolo David
Author-email: dandolodavid@gmail.com
License: BSD 4-clause
Platform: UNKNOWN
Classifier: Development Status :: 5 - Production/Stable
Classifier: Intended Audience :: Science/Research
Classifier: Intended Audience :: Information Technology
Classifier: Intended Audience :: Legal Industry
Classifier: Intended Audience :: Manufacturing
Classifier: License :: OSI Approved :: BSD License
Classifier: Programming Language :: Python :: 3
Classifier: Programming Language :: Python :: 3.4
Classifier: Programming Language :: Python :: 3.5
Requires-Dist: numpy
Requires-Dist: pandas
Requires-Dist: plotly (>4.0.0)
